[
    {
        "id": 6491,
        "merchant_id": 1,
        "user_id": 200812,
        "openid": "oyUt-vz23O-ICtM_LFQ3AAQOHMTo",
        "lodgement_id": "APS-20250922-133231-40026",
        "transaction_id": "106560000450202509222052499203",
        "out_transaction_id": "4200002827202509226166914530",
        "user_reference": "4664554818836",
        "biller_code": "5660",
        "anzsic_code": "2700",
        "short_name": "ORIGIN QLD LPG",
        "long_name": "ORIGIN ENERGY LIMITED QLD LPG",
        "reference_number": "1005049740",
        "real_amount": "146.19",
        "amount": "144.00",
        "fee": 2.19,
        "processing_fee": "0.00",
        "pay_merchant_id": "106560000450",
        "pay_status": 200,
        "pay_service": "wechat",
        "pay_type": "native",
        "pay_channel": "swift",
        "pay_time": "2025-09-22T05:32:43.000000Z",
        "refund_time": null,
        "bpay_channel": "gobill",
        "bpay_time": null,
        "bpay_status": 200,
        "bpay_msg": "bpay payment scheduled successfully",
        "order_source": "PC",
        "causer_ip": "101.115.177.122",
        "created_at": "2025-09-22T05:32:31.000000Z",
        "updated_at": "2025-09-22T05:32:46.000000Z",
        "deleted_at": null,
        "transaction_date": "2025-09-22T05:32:43.000000Z",
        "pay_status_label": "Paid",
        "pay_status_display": "processing",
        "pay_service_label": "Wechat Pay",
        "bill_status_label": "Awaiting Funds"
    },
    {
        "id": 5528,
        "merchant_id": 1,
        "user_id": 200812,
        "openid": "oyUt-vz23O-ICtM_LFQ3AAQOHMTo",
        "lodgement_id": "APS-20250819-101416-82969",
        "transaction_id": "106560000450202508192021716590",
        "out_transaction_id": "4200002758202508191446872831",
        "user_reference": "5168767826588",
        "biller_code": "868745",
        "anzsic_code": "2811",
        "short_name": "GCCC - WATER",
        "long_name": "GOLD COAST CITY COUNCIL - WATER",
        "reference_number": "840086042",
        "real_amount": "507.61",
        "amount": "500.00",
        "fee": 7.61,
        "processing_fee": "0.00",
        "pay_merchant_id": "106560000450",
        "pay_status": 200,
        "pay_service": "wechat",
        "pay_type": "native",
        "pay_channel": "swift",
        "pay_time": "2025-08-19T02:14:37.000000Z",
        "refund_time": null,
        "bpay_channel": "gobill",
        "bpay_time": "2025-08-21T08:00:11.000000Z",
        "bpay_status": 300,
        "bpay_msg": "bpay payment scheduled successfully",
        "order_source": "PC",
        "causer_ip": "101.115.185.69",
        "created_at": "2025-08-19T02:14:17.000000Z",
        "updated_at": "2025-08-21T08:00:11.000000Z",
        "deleted_at": null,
        "transaction_date": "2025-08-21T08:00:11.000000Z",
        "pay_status_label": "Paid",
        "pay_status_display": "completed",
        "pay_service_label": "Wechat Pay",
        "bill_status_label": "Completed"
    }
]